e2b_connect/__init__.py
e2b_connect/client.py
ucloud_sandbox/__init__.py
ucloud_sandbox/api/__init__.py
ucloud_sandbox/api/client/__init__.py
ucloud_sandbox/api/client/api/__init__.py
ucloud_sandbox/api/client/api/sandboxes/__init__.py
ucloud_sandbox/api/client/api/sandboxes/delete_sandboxes_sandbox_id.py
ucloud_sandbox/api/client/api/sandboxes/get_sandboxes.py
ucloud_sandbox/api/client/api/sandboxes/get_sandboxes_metrics.py
ucloud_sandbox/api/client/api/sandboxes/get_sandboxes_sandbox_id.py
ucloud_sandbox/api/client/api/sandboxes/get_sandboxes_sandbox_id_logs.py
ucloud_sandbox/api/client/api/sandboxes/get_sandboxes_sandbox_id_metrics.py
ucloud_sandbox/api/client/api/sandboxes/get_v2_sandboxes.py
ucloud_sandbox/api/client/api/sandboxes/post_sandboxes.py
ucloud_sandbox/api/client/api/sandboxes/post_sandboxes_sandbox_id_connect.py
ucloud_sandbox/api/client/api/sandboxes/post_sandboxes_sandbox_id_pause.py
ucloud_sandbox/api/client/api/sandboxes/post_sandboxes_sandbox_id_refreshes.py
ucloud_sandbox/api/client/api/sandboxes/post_sandboxes_sandbox_id_resume.py
ucloud_sandbox/api/client/api/sandboxes/post_sandboxes_sandbox_id_timeout.py
ucloud_sandbox/api/client/api/templates/__init__.py
ucloud_sandbox/api/client/api/templates/delete_templates_template_id.py
ucloud_sandbox/api/client/api/templates/get_templates.py
ucloud_sandbox/api/client/api/templates/get_templates_template_id.py
ucloud_sandbox/api/client/api/templates/get_templates_template_id_builds_build_id_status.py
ucloud_sandbox/api/client/api/templates/get_templates_template_id_files_hash.py
ucloud_sandbox/api/client/api/templates/patch_templates_template_id.py
ucloud_sandbox/api/client/api/templates/post_templates.py
ucloud_sandbox/api/client/api/templates/post_templates_template_id.py
ucloud_sandbox/api/client/api/templates/post_templates_template_id_builds_build_id.py
ucloud_sandbox/api/client/api/templates/post_v2_templates.py
ucloud_sandbox/api/client/api/templates/post_v3_templates.py
ucloud_sandbox-1.1.0.dist-info/METADATA
ucloud_sandbox-1.1.0.dist-info/WHEEL
ucloud_sandbox-1.1.0.dist-info/licenses/LICENSE
ucloud_sandbox-1.1.0.dist-info/RECORD
