Metadata-Version: 2.4
Name: ucloud_sandbox
Version: 1.1.0
Summary: UCloud Sandbox SDK - Cloud sandbox environments for AI agents
License: MIT
License-File: LICENSE
Author: UCloud
Author-email: support@ucloud.cn
Requires-Python: >=3.9,<4.0
Classifier: License :: OSI Approved :: MIT License
Classifier: Programming Language :: Python :: 3
Classifier: Programming Language :: Python :: 3.9
Classifier: Programming Language :: Python :: 3.10
Classifier: Programming Language :: Python :: 3.11
Classifier: Programming Language :: Python :: 3.12
Classifier: Programming Language :: Python :: 3.13
Classifier: Programming Language :: Python :: 3.14
Requires-Dist: attrs (>=23.2.0)
Requires-Dist: dockerfile-parse (>=2.0.1,<3.0.0)
Requires-Dist: httpcore (>=1.0.5,<2.0.0)
Requires-Dist: httpx (>=0.27.0,<1.0.0)
Requires-Dist: packaging (>=24.1)
Requires-Dist: pillow (>=11.1.0,<12.0.0)
Requires-Dist: protobuf (>=4.21.0)
Requires-Dist: python-dateutil (>=2.8.2)
Requires-Dist: requests (>=2.32.3,<3.0.0)
Requires-Dist: rich (>=14.0.0)
Requires-Dist: typing-extensions (>=4.1.0)
Requires-Dist: wcmatch (>=10.1,<11.0)
Project-URL: Bug Tracker, https://github.com/ucloud/ucloud-sandbox-sdk/issues
Project-URL: Homepage, https://ucloud.cn/
Project-URL: Repository, https://github.com/ucloud/ucloud-sandbox-sdk
